pyLLE/ComputeLLE.jl
pyLLE/__init__.py
pyLLE/_analyzedisp.py
pyLLE/_llesolver.py
pyLLE-4.0.1.dist-info/METADATA
pyLLE-4.0.1.dist-info/WHEEL
pyLLE-4.0.1.dist-info/top_level.txt
pyLLE-4.0.1.dist-info/RECORD
