Metadata-Version: 2.1
Name: pyLLE
Version: 4.0.1
Summary: LLE Solver
Home-page: https://github.com/gregmoille/pyLLE
Author: Greg Moille
Author-email: gmoille@umed.gov
License: Open
Classifier: Programming Language :: Python :: 3
Classifier: License :: OSI Approved
Classifier: Operating System :: OS Independent
Requires-Dist: scipy
Requires-Dist: plotly
Requires-Dist: numpy
Requires-Dist: matplotlib
Requires-Dist: h5py
Requires-Dist: prettytable
Requires-Dist: ipdb
